pynexus/__init__.py
pynexus/jsocket.py
pynexus/net.py
pynexus/pynexus.py
pynexus/version.py
pynexus-1.3.15.dist-info/COPYING
pynexus-1.3.15.dist-info/METADATA
pynexus-1.3.15.dist-info/WHEEL
pynexus-1.3.15.dist-info/top_level.txt
pynexus-1.3.15.dist-info/RECORD
